bought/__init__.py
bought/__main__.py
bought/config.py
bought/sounds/__init__.py
bought/sounds/alert.mp3
bought/sounds/play.py
bought/sounds/success.mp3
bought/websites/__init__.py
bought/websites/newegg.py
bought-0.1.5.dist-info/entry_points.txt
bought-0.1.5.dist-info/LICENSE
bought-0.1.5.dist-info/WHEEL
bought-0.1.5.dist-info/METADATA
bought-0.1.5.dist-info/RECORD
