Metadata-Version: 2.1
Name: bought
Version: 0.1.5
Summary: A bot that purchases items, rendering them bought.
Home-page: https://github.com/boughts/bought
License: GPL v3
Author: Jason G. Villanueva
Author-email: a@jsonvillanueva.com
Requires-Python: >=3.7,<4.0
Classifier: Development Status :: 1 - Planning
Classifier: License :: OSI Approved :: GNU General Public License v3 or later (GPLv3+)
Classifier: License :: Other/Proprietary License
Classifier: Natural Language :: English
Classifier: Programming Language :: Python :: 3
Classifier: Programming Language :: Python :: 3.7
Classifier: Programming Language :: Python :: 3.8
Classifier: Programming Language :: Python :: 3.9
Requires-Dist: click
Requires-Dist: lxml
Requires-Dist: playsound
Requires-Dist: requests
Requires-Dist: selenium
Project-URL: Repository, https://github.com/boughts/bought
